cl_wrangler/__init__.py
cl_wrangler/__main__.py
cl_wrangler-0.2.2.dist-info/METADATA
cl_wrangler-0.2.2.dist-info/WHEEL
cl_wrangler-0.2.2.dist-info/entry_points.txt
cl_wrangler-0.2.2.dist-info/top_level.txt
cl_wrangler-0.2.2.dist-info/RECORD
