Metadata-Version: 2.4
Name: cl-wrangler
Version: 0.2.2
Summary: Switch between multiple Cloudflare/Wrangler accounts
Author: groo.dev
License: MIT
Project-URL: Homepage, https://docs.groo.dev/cl-wrangler
Project-URL: Documentation, https://docs.groo.dev/cl-wrangler
Project-URL: Repository, https://github.com/groo-dev/cl-wrangler
Project-URL: Issues, https://github.com/groo-dev/cl-wrangler/issues
Keywords: cloudflare,wrangler,cli,account-switcher
Classifier: Development Status :: 4 - Beta
Classifier: Environment :: Console
Classifier: Intended Audience :: Developers
Classifier: License :: OSI Approved :: MIT License
Classifier: Operating System :: MacOS
Classifier: Operating System :: POSIX :: Linux
Classifier: Operating System :: Microsoft :: Windows
Classifier: Programming Language :: Python :: 3
Classifier: Programming Language :: Python :: 3.10
Classifier: Programming Language :: Python :: 3.11
Classifier: Programming Language :: Python :: 3.12
Classifier: Topic :: Software Development :: Build Tools
Requires-Python: >=3.10
